{"content": "tears before telling Sanji to run. By letting him glimpse into her mind, she revealed that Doflamingo never resigned his Warlord title or abdicated his throne, which CP0 had revealed to the citizens earlier. She told him to get his crew off the island, and Sanji contacted Law about Doflamingo's deception. However, it was too late, as Doflamingo and a group of Marines led by Fujitora confronted Law on the coast of Green Bit.", "metadata": {"source": "database/Dressrosa Arc.txt", "title": "Dressrosa Arc", "Chapters": "Chapters 700 to 801"}}