{"content": "As Zoro fought Kaku, the other two agents soon found that the Seraphim had followed them by their own discretion and realized that they could not send them back down as the defense system has reactivated. Meanwhile, Kaku entered his awakened form and fought Zoro though the swordsman repelled him. Knowing that they would lose control if a Vegapunk were to give the Seraphim a direct command, Lucci ordered the cyborgs to destroy the lab before the scientists could get their chance.", "metadata": {"source": "database/Egghead Arc.txt", "title": "Egghead Arc", "Chapters": "Chapters 1058 to Current"}}