{"content": "The pirates continue to press on to the bay, trying to keep the path that Little Oars Jr. opened up from being closed. Suddenly, Whitey Bay, the \"Ice Witch\" crashes an icebreaker ship into another part of. With the bay breached on both sides, the pirates rush forward. An officer reports this to Sengoku, who comments that it does not matter. He calls Tsuru, who is literally hanging out several pirates to dry as if they were laundry.", "metadata": {"source": "database/Marineford Arc.txt", "title": "Marineford Arc", "Chapters": "Chapters 550 to 580"}}