{"content": "As all this goes on, Nami explains how the coating works, Telling the crew that it works against water pressure but that the ship will no longer be buoyant. Once the floating bag is removed, the ship will sink. Franky then removes the bag, and Nami orders everyone to raise the sail, which confuses Usopp. Robin explains that the underwater currents work similarly to wind on a coated ship. Once Luffy is told they are ready to leave, he thanks the crew for putting up with his \"selfish wish\" for the last two years. With that, the Thousand Sunny dives underwater. The crew on the Marine ship frantically tries to get their captain to go after them, but he is too smitten by Hancock to notice.\n\nLuffy then gives the order to set sail, and the Straw Hats, reunited after two years, continue their journey to the New World. Their next stop: Fish-Man Island!\n\nStory Impact", "metadata": {"source": "database/Return to Sabaody Arc.txt", "title": "Return to Sabaody Arc", "Chapters": "Chapters 598 to 602"}}