{"content": "Chopper goes into Arm Point and attacks a fish and using a new technique - Kokutei Diamond, which leaves a diamond-shaped impression on the fish's skin, while Franky uses Strong Hammer on a rider, after the above-mentioned realizes that bullets do not affect him. Camie and Pappag watch the battle, amazed by the strength of the Straw Hat crew. Usopp advises Franky that they must dock the ship because the riders have an advantage on open sea and Franky agrees with him but tells him that they can't because the Flying Fish Riders aren't giving them enough time to steer the ship.\n\nLuffy appears running towards Zoro, Brook, Hatchan, Camie and Pappag, announcing that a giant iron masked man on a giant cow is approaching them, when they hear the bull's roar. They realize that it is the Duval's beloved bison, Motobaro.", "metadata": {"source": "database/Sabaody Archipelago Arc.txt", "title": "Sabaody Archipelago Arc", "Chapters": "Chapters 490 to 513"}}