{"content": "Luffy, finding all this hilarious, asks Brook if the skeleton can poop, to which Brook replies yes only for Sanji to berate them both for their choice of questions. Opting for his own take on things, he then starts to shout questions at Brook about what happened to him and the ship, only to be interrupted by Luffy, who much to the shock of everybody else, asks Brook to join his crew. Brook casually agrees to, much to the horror of everyone else present. Leaving the ghost ship with them, Brook goes back with them to the ship and ends up having dinner with the crew. Brook is explaining his Devil Fruit ability when Usopp (in Exorcist attire) notices that he has no shadow and no reflection.", "metadata": {"source": "database/Thriller Bark Arc.txt", "title": "Thriller Bark Arc", "Chapters": "Chapters 442 to 489"}}