{"content": "Zoro woke up in a house in the Northern Cemetery, where he found himself being tended to by Komurasaki. She thanked him and told him about her and Toko's situation, and revealed that she was actually Momonosuke's younger sister Hiyori. Hiyori told Zoro about how she stayed behind in the past to ensure the Kozuki Family bloodline kept going, and was taken care of by Kawamatsu. Zoro wondered about the alliance's next course of action now that Orochi had gained an advantage on them, but went to sleep to help himself heal.", "metadata": {"source": "database/Wano Country Arc.txt", "title": "Wano Country Arc", "Chapters": "Chapters 909 to 1057"}}